packed/__init__.py
packed/_packable.py
packed/_packer.py
packed/_resolver.py
packed/_version.py
packed/py.typed
packed-0.3.0.dist-info/LICENSE.txt
packed-0.3.0.dist-info/METADATA
packed-0.3.0.dist-info/WHEEL
packed-0.3.0.dist-info/top_level.txt
packed-0.3.0.dist-info/RECORD
