Metadata-Version: 2.1
Name: packed
Version: 0.3.0
Summary: Simple serialization and deserialization of custom Python objects using MessagePack
Home-page: https://github.com/tsv1/packed
Author: Nikita Tsvetkov
Author-email: tsv1@fastmail.com
License: Apache-2.0
Classifier: License :: OSI Approved :: Apache Software License
Classifier: Programming Language :: Python :: 3.8
Classifier: Programming Language :: Python :: 3.9
Classifier: Programming Language :: Python :: 3.10
Classifier: Programming Language :: Python :: 3.11
Classifier: Programming Language :: Python :: 3.12
Classifier: Typing :: Typed
Requires-Python: >=3.8
License-File: LICENSE.txt
Requires-Dist: u-msgpack-python<3.0,>=2.5
